{
  "scholar_id": "Lde9BAgAAAAJ",
  "profile_url": "https://scholar.google.com/citations?user=Lde9BAgAAAAJ&hl=en",
  "author_name": "Jon R. Lindsay",
  "author_affiliation": "Associate Professor of International Relations, Georgia Institute of Technology",
  "author_citations": "3703",
  "research_keywords": "International security, cybersecurity, military power, evolution",
  "homepage": "http://www.jonrlindsay.com/",
  "tor_ip_used": "185.243.218.226",
  "scrape_timestamp": "2026-03-24 18:52:58",
  "scrape_method": "direct_scholar_id"
}